acron/__init__.py
acron/job.py
acron/py.typed
acron/scheduler.py
acron-0.2.1.dist-info/LICENSE
acron-0.2.1.dist-info/WHEEL
acron-0.2.1.dist-info/METADATA
acron-0.2.1.dist-info/RECORD
