Metadata-Version: 2.1
Name: acron
Version: 0.2.1
Summary: Lightweight scheduler
Home-page: https://github.com/appgate/acron
License: MIT
Author: Aitor Iturri
Author-email: aitor.iturri@appgate.com
Requires-Python: >=3.6.2,<4.0.0
Classifier: License :: OSI Approved :: MIT License
Classifier: Programming Language :: Python :: 3
Classifier: Programming Language :: Python :: 3.7
Classifier: Programming Language :: Python :: 3.8
Classifier: Programming Language :: Python :: 3.9
Requires-Dist: croniter (>=1.0.15,<2.0.0)
Requires-Dist: dataclasses (>=0.8,<0.9); python_version < "3.7"
